<?xml version="1.0" encoding="utf-8" ?>
<root>
 <CameraPos>
  <Flights>
   <Element>
    <Time>0.000000e+000</Time>
    <Data>
     <Positios>
      <Element>
       <Time>0.000000e+000</Time>
       <Data>
        <Position>
         <Position>
          <x>3.438012e+004</x>
          <y>4.802013e+004</y>
          <z>3.011794e+003</z>
         </Position>
        </Position>
        <InTangent>
         <Position>
          <x>-1.000000e+006</x>
          <y>6.619506e-028</y>
          <z>1.798671e-028</z>
         </Position>
        </InTangent>
        <OutTangent>
         <Position>
          <x>4.614128e+001</x>
          <y>-8.227509e+001</y>
          <z>3.318205e+001</z>
         </Position>
        </OutTangent>
       </Data>
      </Element>
      <Element>
       <Time>6.350000e+000</Time>
       <Data>
        <Position>
         <Position>
          <x>3.632689e+004</x>
          <y>4.454882e+004</y>
          <z>4.411794e+003</z>
         </Position>
        </Position>
        <InTangent>
         <Position>
          <x>5.041797e+002</x>
          <y>-2.463770e+003</y>
          <z>7.000000e+002</z>
         </Position>
        </InTangent>
        <OutTangent>
         <Position>
          <x>5.041797e+002</x>
          <y>-2.463770e+003</y>
          <z>7.000000e+002</z>
         </Position>
        </OutTangent>
       </Data>
      </Element>
      <Element>
       <Time>1.350000e+001</Time>
       <Data>
        <Position>
         <Position>
          <x>3.538848e+004</x>
          <y>4.309259e+004</y>
          <z>4.411794e+003</z>
         </Position>
        </Position>
        <InTangent>
         <Position>
          <x>-2.231221e+003</x>
          <y>-6.491699e+002</y>
          <z>0.000000e+000</z>
         </Position>
        </InTangent>
        <OutTangent>
         <Position>
          <x>-2.231221e+003</x>
          <y>-6.491699e+002</y>
          <z>0.000000e+000</z>
         </Position>
        </OutTangent>
       </Data>
      </Element>
      <Element>
       <Time>2.160000e+001</Time>
       <Data>
        <Position>
         <Position>
          <x>3.186445e+004</x>
          <y>4.325048e+004</y>
          <z>4.411794e+003</z>
         </Position>
        </Position>
        <InTangent>
         <Position>
          <x>-5.213155e+003</x>
          <y>-2.267055e+003</y>
          <z>5.000000e+002</z>
         </Position>
        </InTangent>
        <OutTangent>
         <Position>
          <x>-5.213155e+003</x>
          <y>-2.267055e+003</y>
          <z>5.000000e+002</z>
         </Position>
        </OutTangent>
       </Data>
      </Element>
      <Element>
       <Time>2.960000e+001</Time>
       <Data>
        <Position>
         <Position>
          <x>2.496217e+004</x>
          <y>3.855848e+004</y>
          <z>5.411794e+003</z>
         </Position>
        </Position>
        <InTangent>
         <Position>
          <x>-4.095609e+003</x>
          <y>-3.691756e+003</y>
          <z>3.000000e+002</z>
         </Position>
        </InTangent>
        <OutTangent>
         <Position>
          <x>-4.095609e+003</x>
          <y>-3.691756e+003</y>
          <z>3.000000e+002</z>
         </Position>
        </OutTangent>
       </Data>
      </Element>
      <Element>
       <Time>3.505000e+001</Time>
       <Data>
        <Position>
         <Position>
          <x>2.367323e+004</x>
          <y>3.586697e+004</y>
          <z>5.011794e+003</z>
         </Position>
        </Position>
        <InTangent>
         <Position>
          <x>4.281163e+001</x>
          <y>8.939754e+001</y>
          <z>1.328585e+001</z>
         </Position>
        </InTangent>
        <OutTangent>
         <Position>
          <x>-1.000000e+006</x>
          <y>2.960000e+001</y>
          <z>1.000000e-010</z>
         </Position>
        </OutTangent>
       </Data>
      </Element>
     </Positios>
    </Data>
   </Element>
   <Element>
    <Time>3.600000e+001</Time>
    <Data>
     <Positios>
      <Element>
       <Time>0.000000e+000</Time>
       <Data>
        <Position>
         <Position>
          <x>2.895589e+004</x>
          <y>4.269070e+004</y>
          <z>2.561795e+003</z>
         </Position>
        </Position>
        <InTangent>
         <Position>
          <x>-1.000000e+006</x>
          <y>6.664939e-028</y>
          <z>6.664996e-028</z>
         </Position>
        </InTangent>
        <OutTangent>
         <Position>
          <x>9.288659e+001</x>
          <y>3.501688e+001</y>
          <z>1.205271e+001</z>
         </Position>
        </OutTangent>
       </Data>
      </Element>
      <Element>
       <Time>4.362347e+000</Time>
       <Data>
        <Position>
         <Position>
          <x>2.972656e+004</x>
          <y>4.298123e+004</y>
          <z>2.661795e+003</z>
         </Position>
        </Position>
        <InTangent>
         <Position>
          <x>1.204404e+003</x>
          <y>6.781953e+002</y>
          <z>2.750035e+002</z>
         </Position>
        </InTangent>
        <OutTangent>
         <Position>
          <x>1.204404e+003</x>
          <y>6.781953e+002</y>
          <z>2.750035e+002</z>
         </Position>
        </OutTangent>
       </Data>
      </Element>
      <Element>
       <Time>1.256357e+001</Time>
       <Data>
        <Position>
         <Position>
          <x>3.136470e+004</x>
          <y>4.404709e+004</y>
          <z>3.111802e+003</z>
         </Position>
        </Position>
        <InTangent>
         <Position>
          <x>1.717624e+003</x>
          <y>3.941504e+002</y>
          <z>3.540039e-003</z>
         </Position>
        </InTangent>
        <OutTangent>
         <Position>
          <x>1.717624e+003</x>
          <y>3.941504e+002</y>
          <z>3.540039e-003</z>
         </Position>
        </OutTangent>
       </Data>
      </Element>
      <Element>
       <Time>1.985000e+001</Time>
       <Data>
        <Position>
         <Position>
          <x>3.316181e+004</x>
          <y>4.376953e+004</y>
          <z>2.661802e+003</z>
         </Position>
        </Position>
        <InTangent>
         <Position>
          <x>-9.593288e+001</x>
          <y>1.481657e+001</y>
          <z>2.402180e+001</z>
         </Position>
        </InTangent>
        <OutTangent>
         <Position>
          <x>-1.000000e+006</x>
          <y>1.256357e+001</y>
          <z>1.000000e-010</z>
         </Position>
        </OutTangent>
       </Data>
      </Element>
     </Positios>
    </Data>
   </Element>
   <Element>
    <Time>5.600000e+001</Time>
    <Data>
     <Positios>
      <Element>
       <Time>0.000000e+000</Time>
       <Data>
        <Position>
         <Position>
          <x>3.659407e+004</x>
          <y>2.093836e+004</y>
          <z>3.361801e+003</z>
         </Position>
        </Position>
        <InTangent>
         <Position>
          <x>-1.000000e+006</x>
          <y>7.031116e-028</y>
          <z>1.782079e-028</z>
         </Position>
        </InTangent>
        <OutTangent>
         <Position>
          <x>4.245956e+001</x>
          <y>-9.006725e+001</y>
          <z>9.207119e+000</z>
         </Position>
        </OutTangent>
       </Data>
      </Element>
      <Element>
       <Time>1.150000e+001</Time>
       <Data>
        <Position>
         <Position>
          <x>3.936103e+004</x>
          <y>1.506895e+004</y>
          <z>3.961801e+003</z>
         </Position>
        </Position>
        <InTangent>
         <Position>
          <x>-4.245956e+001</x>
          <y>9.006725e+001</y>
          <z>-9.207119e+000</z>
         </Position>
        </InTangent>
        <OutTangent>
         <Position>
          <x>-1.000000e+006</x>
          <y>1.836071e-038</y>
          <z>1.742464e-039</z>
         </Position>
        </OutTangent>
       </Data>
      </Element>
     </Positios>
    </Data>
   </Element>
   <Element>
    <Time>7.000000e+001</Time>
    <Data>
     <Positios>
      <Element>
       <Time>0.000000e+000</Time>
       <Data>
        <Position>
         <Position>
          <x>2.213738e+004</x>
          <y>4.164770e+004</y>
          <z>2.761802e+003</z>
         </Position>
        </Position>
        <InTangent>
         <Position>
          <x>-1.000000e+006</x>
          <y>1.016067e-027</y>
          <z>7.418913e-028</z>
         </Position>
        </InTangent>
        <OutTangent>
         <Position>
          <x>-9.267699e+001</x>
          <y>-3.542543e+001</y>
          <z>1.254356e+001</z>
         </Position>
        </OutTangent>
       </Data>
      </Element>
      <Element>
       <Time>7.050000e+000</Time>
       <Data>
        <Position>
         <Position>
          <x>2.102912e+004</x>
          <y>4.122407e+004</y>
          <z>2.911802e+003</z>
         </Position>
        </Position>
        <InTangent>
         <Position>
          <x>9.267699e+001</x>
          <y>3.542543e+001</y>
          <z>-1.254356e+001</z>
         </Position>
        </InTangent>
        <OutTangent>
         <Position>
          <x>-1.000000e+006</x>
          <y>1.836071e-038</y>
          <z>1.742464e-039</z>
         </Position>
        </OutTangent>
       </Data>
      </Element>
     </Positios>
    </Data>
   </Element>
   <Element>
    <Time>7.800000e+001</Time>
    <Data>
     <Positios>
      <Element>
       <Time>0.000000e+000</Time>
       <Data>
        <Position>
         <Position>
          <x>3.480004e+004</x>
          <y>1.283594e+004</y>
          <z>3.211802e+003</z>
         </Position>
        </Position>
        <InTangent>
         <Position>
          <x>-1.000000e+006</x>
          <y>1.254247e-032</y>
          <z>5.956824e-033</z>
         </Position>
        </InTangent>
        <OutTangent>
         <Position>
          <x>-2.637717e+001</x>
          <y>-9.646594e+001</y>
          <z>0.000000e+000</z>
         </Position>
        </OutTangent>
       </Data>
      </Element>
      <Element>
       <Time>9.700000e+000</Time>
       <Data>
        <Position>
         <Position>
          <x>3.420438e+004</x>
          <y>1.065754e+004</y>
          <z>3.211802e+003</z>
         </Position>
        </Position>
        <InTangent>
         <Position>
          <x>2.637717e+001</x>
          <y>9.646594e+001</y>
          <z>0.000000e+000</z>
         </Position>
        </InTangent>
        <OutTangent>
         <Position>
          <x>-1.000000e+006</x>
          <y>1.479066e-038</y>
          <z>1.742453e-039</z>
         </Position>
        </OutTangent>
       </Data>
      </Element>
     </Positios>
    </Data>
   </Element>
  </Flights>
 </CameraPos>
 <CameraLookAt>
  <Flights>
   <Element>
    <Time>0.000000e+000</Time>
    <Data>
     <Positios>
      <Element>
       <Time>0.000000e+000</Time>
       <Data>
        <Position>
         <Position>
          <x>3.377838e+004</x>
          <y>5.432552e+004</y>
          <z>-4.910000e+002</z>
         </Position>
        </Position>
        <InTangent>
         <Position>
          <x>-1.000000e+006</x>
          <y>6.619506e-028</y>
          <z>1.798671e-028</z>
         </Position>
        </InTangent>
        <OutTangent>
         <Position>
          <x>-2.542137e+001</x>
          <y>-9.672070e+001</y>
          <z>0.000000e+000</z>
         </Position>
        </OutTangent>
       </Data>
      </Element>
      <Element>
       <Time>6.350000e+000</Time>
       <Data>
        <Position>
         <Position>
          <x>3.256566e+004</x>
          <y>4.971149e+004</y>
          <z>-4.910000e+002</z>
         </Position>
        </Position>
        <InTangent>
         <Position>
          <x>2.542137e+001</x>
          <y>9.672070e+001</y>
          <z>0.000000e+000</z>
         </Position>
        </InTangent>
        <OutTangent>
         <Position>
          <x>-6.082925e+001</x>
          <y>-7.422646e+001</y>
          <z>-2.809481e+001</z>
         </Position>
        </OutTangent>
       </Data>
      </Element>
      <Element>
       <Time>1.350000e+001</Time>
       <Data>
        <Position>
         <Position>
          <x>2.996749e+004</x>
          <y>4.654109e+004</y>
          <z>-1.691000e+003</z>
         </Position>
        </Position>
        <InTangent>
         <Position>
          <x>6.082925e+001</x>
          <y>7.422646e+001</y>
          <z>2.809481e+001</z>
         </Position>
        </InTangent>
        <OutTangent>
         <Position>
          <x>-7.247885e+001</x>
          <y>-6.769663e+001</y>
          <z>-1.279769e+001</z>
         </Position>
        </OutTangent>
       </Data>
      </Element>
      <Element>
       <Time>2.160000e+001</Time>
       <Data>
        <Position>
         <Position>
          <x>2.543679e+004</x>
          <y>4.230933e+004</y>
          <z>-2.490992e+003</z>
         </Position>
        </Position>
        <InTangent>
         <Position>
          <x>7.247885e+001</x>
          <y>6.769663e+001</y>
          <z>1.279769e+001</z>
         </Position>
        </InTangent>
        <OutTangent>
         <Position>
          <x>-7.648753e+001</x>
          <y>-6.343958e+001</y>
          <z>1.114027e+001</z>
         </Position>
        </OutTangent>
       </Data>
      </Element>
      <Element>
       <Time>2.960000e+001</Time>
       <Data>
        <Position>
         <Position>
          <x>1.857093e+004</x>
          <y>3.661471e+004</y>
          <z>-1.490992e+003</z>
         </Position>
        </Position>
        <InTangent>
         <Position>
          <x>7.648753e+001</x>
          <y>6.343958e+001</y>
          <z>-1.114027e+001</z>
         </Position>
        </InTangent>
        <OutTangent>
         <Position>
          <x>-4.309494e+001</x>
          <y>-8.998911e+001</y>
          <z>-6.686882e+000</z>
         </Position>
        </OutTangent>
       </Data>
      </Element>
      <Element>
       <Time>3.505000e+001</Time>
       <Data>
        <Position>
         <Position>
          <x>1.728199e+004</x>
          <y>3.392320e+004</y>
          <z>-1.690992e+003</z>
         </Position>
        </Position>
        <InTangent>
         <Position>
          <x>4.309494e+001</x>
          <y>8.998911e+001</y>
          <z>6.686882e+000</z>
         </Position>
        </InTangent>
        <OutTangent>
         <Position>
          <x>-1.000000e+006</x>
          <y>2.960000e+001</y>
          <z>1.000000e-010</z>
         </Position>
        </OutTangent>
       </Data>
      </Element>
     </Positios>
    </Data>
   </Element>
   <Element>
    <Time>3.600000e+001</Time>
    <Data>
     <Positios>
      <Element>
       <Time>0.000000e+000</Time>
       <Data>
        <Position>
         <Position>
          <x>3.516541e+004</x>
          <y>4.595074e+004</y>
          <z>-3.409917e+002</z>
         </Position>
        </Position>
        <InTangent>
         <Position>
          <x>-1.000000e+006</x>
          <y>6.664939e-028</y>
          <z>6.664996e-028</z>
         </Position>
        </InTangent>
        <OutTangent>
         <Position>
          <x>2.174603e+001</x>
          <y>9.724003e+001</y>
          <z>8.475404e+000</z>
         </Position>
        </OutTangent>
       </Data>
      </Element>
      <Element>
       <Time>4.362347e+000</Time>
       <Data>
        <Position>
         <Position>
          <x>3.542199e+004</x>
          <y>4.709806e+004</y>
          <z>-2.409917e+002</z>
         </Position>
        </Position>
        <InTangent>
         <Position>
          <x>-2.174603e+001</x>
          <y>-9.724003e+001</y>
          <z>-8.475404e+000</z>
         </Position>
        </InTangent>
        <OutTangent>
         <Position>
          <x>6.407935e+001</x>
          <y>6.345032e+001</y>
          <z>-4.323901e+001</z>
         </Position>
        </OutTangent>
       </Data>
      </Element>
      <Element>
       <Time>1.256357e+001</Time>
       <Data>
        <Position>
         <Position>
          <x>3.682986e+004</x>
          <y>4.849211e+004</y>
          <z>-1.190985e+003</z>
         </Position>
        </Position>
        <InTangent>
         <Position>
          <x>-6.407935e+001</x>
          <y>-6.345032e+001</y>
          <z>4.323901e+001</z>
         </Position>
        </InTangent>
        <OutTangent>
         <Position>
          <x>-7.408595e+001</x>
          <y>6.641927e+001</y>
          <z>1.005686e+001</z>
         </Position>
        </OutTangent>
       </Data>
      </Element>
      <Element>
       <Time>1.985000e+001</Time>
       <Data>
        <Position>
         <Position>
          <x>3.425151e+004</x>
          <y>5.080364e+004</y>
          <z>-8.409850e+002</z>
         </Position>
        </Position>
        <InTangent>
         <Position>
          <x>7.408595e+001</x>
          <y>-6.641927e+001</y>
          <z>-1.005686e+001</z>
         </Position>
        </InTangent>
        <OutTangent>
         <Position>
          <x>-1.000000e+006</x>
          <y>1.256357e+001</y>
          <z>1.000000e-010</z>
         </Position>
        </OutTangent>
       </Data>
      </Element>
     </Positios>
    </Data>
   </Element>
   <Element>
    <Time>5.600000e+001</Time>
    <Data>
     <Positios>
      <Element>
       <Time>0.000000e+000</Time>
       <Data>
        <Position>
         <Position>
          <x>3.867698e+004</x>
          <y>1.384973e+004</y>
          <z>-1.340984e+003</z>
         </Position>
        </Position>
        <InTangent>
         <Position>
          <x>-1.000000e+006</x>
          <y>7.031116e-028</y>
          <z>1.782079e-028</z>
         </Position>
        </InTangent>
        <OutTangent>
         <Position>
          <x>4.245938e+001</x>
          <y>-9.006717e+001</y>
          <z>-9.207119e+000</z>
         </Position>
        </OutTangent>
       </Data>
      </Element>
      <Element>
       <Time>1.150000e+001</Time>
       <Data>
        <Position>
         <Position>
          <x>4.144393e+004</x>
          <y>7.980326e+003</y>
          <z>-1.940984e+003</z>
         </Position>
        </Position>
        <InTangent>
         <Position>
          <x>-4.245938e+001</x>
          <y>9.006717e+001</y>
          <z>9.207119e+000</z>
         </Position>
        </InTangent>
        <OutTangent>
         <Position>
          <x>-1.000000e+006</x>
          <y>1.836071e-038</y>
          <z>1.742464e-039</z>
         </Position>
        </OutTangent>
       </Data>
      </Element>
     </Positios>
    </Data>
   </Element>
   <Element>
    <Time>7.000000e+001</Time>
    <Data>
     <Positios>
      <Element>
       <Time>0.000000e+000</Time>
       <Data>
        <Position>
         <Position>
          <x>2.362290e+004</x>
          <y>4.870602e+004</y>
          <z>-6.540984e+003</z>
         </Position>
        </Position>
        <InTangent>
         <Position>
          <x>-1.000000e+006</x>
          <y>1.016067e-027</y>
          <z>7.418913e-028</z>
         </Position>
        </InTangent>
        <OutTangent>
         <Position>
          <x>1.471831e+000</x>
          <y>-2.466964e+001</y>
          <z>9.689465e+001</z>
         </Position>
        </OutTangent>
       </Data>
      </Element>
      <Element>
       <Time>7.050000e+000</Time>
       <Data>
        <Position>
         <Position>
          <x>2.366771e+004</x>
          <y>4.795494e+004</y>
          <z>-3.590984e+003</z>
         </Position>
        </Position>
        <InTangent>
         <Position>
          <x>-1.471831e+000</x>
          <y>2.466964e+001</y>
          <z>-9.689465e+001</z>
         </Position>
        </InTangent>
        <OutTangent>
         <Position>
          <x>-1.000000e+006</x>
          <y>1.836071e-038</y>
          <z>1.742464e-039</z>
         </Position>
        </OutTangent>
       </Data>
      </Element>
     </Positios>
    </Data>
   </Element>
   <Element>
    <Time>7.800000e+001</Time>
    <Data>
     <Positios>
      <Element>
       <Time>0.000000e+000</Time>
       <Data>
        <Position>
         <Position>
          <x>4.027174e+004</x>
          <y>7.555148e+003</y>
          <z>-2.290984e+003</z>
         </Position>
        </Position>
        <InTangent>
         <Position>
          <x>-1.000000e+006</x>
          <y>1.254247e-032</y>
          <z>5.956824e-033</z>
         </Position>
        </InTangent>
        <OutTangent>
         <Position>
          <x>3.953912e+001</x>
          <y>8.970080e+001</y>
          <z>-1.974204e+001</z>
         </Position>
        </OutTangent>
       </Data>
      </Element>
      <Element>
       <Time>9.700000e+000</Time>
       <Data>
        <Position>
         <Position>
          <x>4.187397e+004</x>
          <y>1.119006e+004</y>
          <z>-3.090984e+003</z>
         </Position>
        </Position>
        <InTangent>
         <Position>
          <x>-3.953912e+001</x>
          <y>-8.970080e+001</y>
          <z>1.974204e+001</z>
         </Position>
        </InTangent>
        <OutTangent>
         <Position>
          <x>-1.000000e+006</x>
          <y>1.479066e-038</y>
          <z>1.742453e-039</z>
         </Position>
        </OutTangent>
       </Data>
      </Element>
     </Positios>
    </Data>
   </Element>
  </Flights>
 </CameraLookAt>
 <LuaFunctions>
  <Flights>
   <Element>
    <Time>0.000000e+000</Time>
    <Data>
     <Element>
      <Time>5.000000e-001</Time>
      <FuncName>Text1</FuncName>
     </Element>
     <Element>
      <Time>1.260000e+001</Time>
      <FuncName>Text2</FuncName>
     </Element>
     <Element>
      <Time>1.305000e+001</Time>
      <FuncName>Text3</FuncName>
     </Element>
     <Element>
      <Time>2.475000e+001</Time>
      <FuncName>Text2</FuncName>
     </Element>
     <Element>
      <Time>2.525000e+001</Time>
      <FuncName>Text4</FuncName>
     </Element>
     <Element>
      <Time>3.495000e+001</Time>
      <FuncName>Text2</FuncName>
     </Element>
    </Data>
   </Element>
   <Element>
    <Time>3.600000e+001</Time>
    <Data>
     <Element>
      <Time>4.319104e-002</Time>
      <FuncName>Text5</FuncName>
     </Element>
     <Element>
      <Time>1.192073e+001</Time>
      <FuncName>Text2</FuncName>
     </Element>
     <Element>
      <Time>1.235264e+001</Time>
      <FuncName>Text6</FuncName>
     </Element>
     <Element>
      <Time>1.935000e+001</Time>
      <FuncName>Text2</FuncName>
     </Element>
    </Data>
   </Element>
   <Element>
    <Time>5.600000e+001</Time>
    <Data>
     <Element>
      <Time>3.775508e-002</Time>
      <FuncName>Text7</FuncName>
     </Element>
     <Element>
      <Time>1.110000e+001</Time>
      <FuncName>Text2</FuncName>
     </Element>
    </Data>
   </Element>
   <Element>
    <Time>7.000000e+001</Time>
    <Data>
     <Element>
      <Time>4.322583e-002</Time>
      <FuncName>Text8</FuncName>
     </Element>
     <Element>
      <Time>6.700000e+000</Time>
      <FuncName>Text2</FuncName>
     </Element>
    </Data>
   </Element>
   <Element>
    <Time>7.800000e+001</Time>
    <Data>
     <Element>
      <Time>5.000000e-002</Time>
      <FuncName>Text9</FuncName>
     </Element>
     <Element>
      <Time>9.600000e+000</Time>
      <FuncName>Text2</FuncName>
     </Element>
    </Data>
   </Element>
  </Flights>
 </LuaFunctions>
</root>
